pyopenexrates/__init__.py
pyopenexrates/client.py
pyopenexrates/exceptions.py
pyopenexrates-0.2.dist-info/METADATA
pyopenexrates-0.2.dist-info/RECORD
pyopenexrates-0.2.dist-info/WHEEL
pyopenexrates-0.2.dist-info/top_level.txt
