Metadata-Version: 2.1
Name: pyopenexrates
Version: 0.2
Summary: An openexchangerates.org service API wrapper for Python
Home-page: https://github.com/intelligems/pyopenexrates
Author: K. Livieratos
Author-email: kostas@intelligems.eu
License: MIT
Platform: UNKNOWN
Classifier: Intended Audience :: Developers
Classifier: Programming Language :: Python :: 3
Requires-Dist: requests (>=2.19.1)
